MANIFEST.in
README.txt
setup.cfg
setup.py
docs/HISTORY.txt
horae/__init__.py
horae.lifecycle.egg-info/PKG-INFO
horae.lifecycle.egg-info/SOURCES.txt
horae.lifecycle.egg-info/dependency_links.txt
horae.lifecycle.egg-info/entry_points.txt
horae.lifecycle.egg-info/namespace_packages.txt
horae.lifecycle.egg-info/not-zip-safe
horae.lifecycle.egg-info/requires.txt
horae.lifecycle.egg-info/top_level.txt
horae/lifecycle/__init__.py
horae/lifecycle/configure.zcml
horae/lifecycle/interfaces.py
horae/lifecycle/latest.py
horae/lifecycle/lifecycle.py
horae/lifecycle/viewlets.py
horae/lifecycle/locales/horae.lifecycle.pot
horae/lifecycle/locales/de/LC_MESSAGES/horae.lifecycle.mo
horae/lifecycle/locales/de/LC_MESSAGES/horae.lifecycle.po
horae/lifecycle/templates/byline.cpt